{"article": "Una mujer de 48 años ha muerto esta mañana en Albox (Almería) y su pareja ha sido detenida, según han informado fuentes de la Delegación del Gobierno en Andalucía. Las fuentes señalan que los primeros indicios indican un caso de violencia machista, en espera de que lo confirme la autopsia que se está practicando a la fallecida, de nacionalidad española. El hombre, de nacionalidad lituana, avisó al servicio de emergencias 112 de que la mujer no respiraba y los sanitarios, al llegar al domicilio indicado, comprobaron que estaba muerta. El varón, pareja de la fallecida, ha sido detenido por la Guardia Civil, porque según los primeros indicios podría tratarse de un caso de violencia machista. A través de una portavoz, el delegado del Gobierno en Andalucía, Antonio Sanz, ha condenado este hecho y ha destacado la unidad de acción contra la lacra de la violencia machista, y ha valorado el Pacto de Estado contra este tipo de violencia.", "title": "Muere una mujer asesinada en Almería y detienen a su pareja", "url": "https://www.elespanol.com/reportajes/20180331/muere-mujer-asesinada-almeria-detienen-pareja/296220722_0.html", "keywords": "Reportajes,Albox,Violencia de género,Mujeres", "date": "2018-03-31", "id": "88e6359d7d5fa59025719437b1b8c36db19ad2e8", "summary": "La Guardia Civil cree que se trata de un caso de violencia machista. El hombre, de nacionalidad lituana, llamó al 112 diciendo que su mujer no respiraba."}